[
    {
        "company": "Virginia State Police",
        "job_title": "Project Manager",
        "location": "Richmond, VA, USA",
        "full_location": {
            "city": "Richmond",
            "state": "VA",
            "country": "USA"
        },
        "job_details": {
            "employment_type": [
                "third party"
            ],
            "job_code": "",
            "experience_required": "10+ years",
            "degree_required": "Not specified",
            "visa_sponsorship": "Not specified",
            "notice_period": "Not specified",
            "duration": "Not specified",
            "rate": "Not specified"
        },
        "skills": {
            "core": [
                "Project Management Professional (PMP) certification",
                "Project management experience",
                "Proficient with Microsoft Word and Excel",
                "High-risk project management experience",
                "Completion of a Category 1 or 2 Commonwealth project of $5M or more"
            ],
            "primary": [
                "Documented high-risk project management experience",
                "Managing multiple projects",
                "Process optimization",
                "Change management",
                "Interpersonal skills",
                "Oral/written communication skills",
                "Presentation skills",
                "Extensive knowledge of applications development"
            ],
            "secondary": [
                "Facilitation",
                "Internal/external consulting"
            ],
            "all": [
                "Project Management Professional (PMP) certification",
                "Project management experience",
                "Proficient with Microsoft Word and Excel",
                "High-risk project management experience",
                "Completion of a Category 1 or 2 Commonwealth project of $5M or more",
                "Documented high-risk project management experience",
                "Managing multiple projects",
                "Process optimization",
                "Change management",
                "Interpersonal skills",
                "Oral/written communication skills",
                "Presentation skills",
                "Extensive knowledge of applications development",
                "Facilitation",
                "Internal/external consulting"
            ]
        },
        "job_type": [
            "onsite"
        ],
        "contact_person": "John Joseph",
        "email": "john.joseph@idctechnologies.com",
        "jd": "From: John Joseph, IDC Technologies.com john.joseph@idctechnologies.com Reply to: john.joseph@idctechnologies.com The Virginia State Police is looking for a Project Manager with 10+ years of experience in the field. A PM is needed to address and coordinate the replacement of the existing criminal history systems utilized by the Virginia State Police. The Project Manager will work with Business Analysts, program manager and serve as the liaison between the business community/end users and the IT organization. The project manager is responsible for managing the project scope, schedule and budget and reporting to VSP IT management and the business stakeholders/owners on a weekly basis or as agreed upon. The successful candidate must have the following qualifications: * Active Project Management Institute (PMI) Project Management Professional (PMP)certification REQUIRED * Documented high-risk project management experience * Completion of a Category 1 or 2 Commonwealth project of $5M or more, OR completion of non-COV project with a value greater than $10M as PM of record. Duties may include managing/coordinating a Request for Proposal (RFP) process composed of RFP related tasks such the review and assistance with drafting of the evaluation criteria, contract terms, RFP format, and other procurement-related documentation in coordination with the VSP procurement staff. The project manager will assist the VSP IT Division staff in responding to vendor queries, performing the vendor evaluation process and contract negotiations as necessary. The PM will direct the Business Analyst throughout the project to ensure the objectives and requirements for a new system are fully defined. The PM will oversee the vendor efforts on the design, development and implementation of the solution and will coordinate with the vendor PM and VSP IT Division and business stakeholders/owners as needed. The Project Manager, in coordination with the Business Analyst, will be responsible for the identification, analysis, tracking and recommending appropriate actions to project issues including those that are technology related. They will also be responsible for the identification and management of project risks. The PM, coordinating with the VSP IT Division, will provide overall direction to the vendor as to any interfaces to existing VSP (and non-Agency) systems. In general, the PM is responsible for the coordination and completion of the assigned projects that will result in the design, execution, delivery and implementation of a new VSP criminal history system. Skills Matrix -Skill Required / Desired Amount of ExperienceReview, analyze and evaluate user/system needs Required 10 YearsProject management experience with a PMP Certification. Required 10 YearsProficient with Microsoft Word and XL Required 10 YearsDemonstrated ability to manage multiple projects lasting 6 to 12 months, with teams of 3 to 4 people. Required 10 YearsProcess optimization, best practices, change management, facilitation and internal/external consulting is highly preferred. Required 10 YearsShould have excellent interpersonal, oral/written communication and presentation skills. Required 10 YearsExtensive knowledge of applications development Required 10 YearsDocumented high risk management experience Required 10 YearsCompletion of a Category 1 or 2 Commonwealth project of $5M or more, or completion of non-COV project with a value greater than $10M as PM of record. Required 10 Years.",
        "source": "Email",
        "date_posted": "2024-10-01 11:19:11-05:00",
        "unique_id": "19248e54abb3e472",
        "emp_type": [
            "third party"
        ],
        "tag": "Project Manager"
    }
]