[
    {
        "company": "TTDATA LLC",
        "job_title": ".NET Solutions Architect",
        "location": "NYC, NY, USA",
        "full_location": {
            "city": "NYC",
            "state": "NY",
            "country": "USA"
        },
        "job_details": {
            "employment_type": [],
            "job_code": "",
            "experience_required": "",
            "degree_required": "",
            "visa_sponsorship": "Need only Visa independent candidates",
            "notice_period": "",
            "duration": "6 Months CTH",
            "rate": ""
        },
        "skills": {
            "core": [
                ".NET",
                "C#",
                "ASP.NET",
                "SQL Server",
                "Object Oriented Design",
                "Entity Framework",
                "MVC",
                "WCF RIA Services",
                "Unit Testing",
                "UML",
                "CSS",
                "JavaScript",
                "REST Web Services",
                "Windows Workflow Foundation",
                "Test-Driven Development",
                "Technical Documentation",
                "Communication Skills",
                "Time Management",
                "Problem-Solving"
            ],
            "primary": [
                ".NET",
                "C#",
                "ASP.NET"
            ],
            "secondary": [
                "REST/SOAP",
                "TDD",
                "BDD",
                "Testing Frameworks",
                "Source Control",
                "Power BI",
                "AWS CI/CD"
            ],
            "all": [
                ".NET",
                "C#",
                "ASP.NET",
                "SQL Server",
                "Object Oriented Design",
                "Entity Framework",
                "MVC",
                "WCF RIA Services",
                "Unit Testing",
                "UML",
                "CSS",
                "JavaScript",
                "REST Web Services",
                "Windows Workflow Foundation",
                "Test-Driven Development",
                "Technical Documentation",
                "Communication Skills",
                "Time Management",
                "Problem-Solving",
                "REST/SOAP",
                "TDD",
                "BDD",
                "Testing Frameworks",
                "Source Control",
                "Power BI",
                "AWS CI/CD"
            ],
            "with_experience": [
                ".NET",
                "C#",
                "ASP.NET"
            ]
        },
        "job_type": [
            "onsite"
        ],
        "contact_person": "Ganesh",
        "email": "ganesh@ttdatas.com",
        "jd": "From: Ganesh, TTDATA LLC ganesh@ttdatas.com Reply to: ganesh@ttdatas.com Note: Kindly share the profile to ganesh@ttdatas.com Title: .NET Solutions Architect\nLocation: NYC, NY(Onsite)\nDuration: 6 Months CTH\nNeed only Visa independent candidates Key Competencies: Hands on experience in Object Oriented analysis and design using common design patterns Hands on experience in designing and developing applications using .NET 3.5/4 development using C# and ASP.NET Competence in SQL Server Competence in Object Oriented design and development techniques Working knowledge in Entity Framework, MVC Working knowledge in Microsoft WCF RIA services Knowledge in Unit testing using nUnit or similar Competence in UML \u2013 Sequence diagrams, Class diagrams, etc Working Knowledge in requirements analysis or business analysis techniques Working knowledge in CSS, Java scripting Experience in REST web services Experience in Microsoft windows workflow foundations Experience with test-driven development Client-focused, working independently and simultaneously across multiple projects Capture and documentation of customer requirements and transformation into software design specifications / user stories Writes structured well-documented code to deliver scalable software solutions Good communication, able to write clear and concise documentation for technical and nontechnical audiences Team player with effective time management Strong problem-solving skills and attention to detail Ability to peer review and provide feedback on others work Consistently technically abreast of existing, new and emerging technologies to complement solutions Willing to be flexible with shift Key Activities Creating detailed technical design documentation & estimates Implementing unit tests Develop code as per the specifications and coding standards Ensure all code passes unit testing with appropriate code coverage Peer reviews of other team members\u2019 code Provide feedback on process to refine where necessary Liaise with Architects, Testers and any other project stakeholders both verbally and in writing Technical support Key Technologies Experience in the following technologies is required: Microsoft .NET 3.5/4 C# ASP.NET VB .NET Relational Databases like MS SQL Server Web frameworks like MVC ASP.NET Core and Web API Experience in the following technologies is desirable: Integrating websites with 3rd party APIs (REST/SOAP) TDD / BDD (e.g. Cucumber) Testing frameworks Source Control (SVN, TFS) Release Management Power BI and Analytics AWS continuous integration and continuous delivery (CI/CD)",
        "source": "Email",
        "date_posted": "2024-09-30 12:07:27-05:00",
        "unique_id": "19243e809fefe151",
        "tag": ".NET Dev"
    }
]