[
    {
        "company": "Synkriom",
        "job_title": "Business Analyst",
        "location": "Saint Petersburg, FL, USA",
        "full_location": {
            "city": "Saint Petersburg",
            "state": "FL",
            "country": "USA"
        },
        "job_details": {
            "employment_type": [
                "full-time",
                "third party"
            ],
            "experience_required": "5 years",
            "degree_required": "Not specified",
            "visa_sponsorship": "Not specified",
            "notice_period": "Not specified",
            "duration": "Not specified",
            "rate": "Not specified"
        },
        "skills": {
            "core": [
                "Business Analysis",
                "Manufacturing Industry Knowledge",
                "Process Mapping",
                "Requirement Gathering",
                "Industrial IoT"
            ],
            "primary": [
                "Production Knowledge",
                "Quality Knowledge",
                "Inventory Knowledge",
                "Maintenance Knowledge",
                "Agile Framework"
            ],
            "secondary": [
                "Communication Skills",
                "Analytical Skills",
                "MES Applications Knowledge"
            ],
            "all": [
                "Business Analysis",
                "Manufacturing Industry Knowledge",
                "Process Mapping",
                "Requirement Gathering",
                "Industrial IoT",
                "Production Knowledge",
                "Quality Knowledge",
                "Inventory Knowledge",
                "Maintenance Knowledge",
                "Agile Framework",
                "Communication Skills",
                "Analytical Skills",
                "MES Applications Knowledge"
            ]
        },
        "job_type": [
            "onsite"
        ],
        "contact_person": "Shivangi Tripathi",
        "email": "shivangi.tripathi@synkriom.com",
        "jd": "Hi, Kindly go through the JD Business AnalystMust Have Technical/Functional Skills \u2022 Min of 5 years of experience in Business Analyst role in manufacturing industry for development of applications used on shop floor\u2022 Strong knowledge of business processes in one of the industries viz. Automotive, CPG, Chemical process, Hi-Tech manufacturing, Medical Devices \u2013 PREFER experience Semiconductor industry\u2022 Good understanding of Production, Quality, Inventory and Maintenance capabilities required for these industries\u2022 Experience in creating business process maps and detailed process flow diagrams\u2022 Good understanding of Production, Quality, Inventory and Maintenance functions\u2022 Ability to conduct requirement gathering sessions and prepare FRS\u2022 Understanding of Industrial IoT and Industry 4.0 \u2022 Understanding of one of MES applications like DS Apriso, Siemens Opcenter, GE Proficy, SAP ME/MII, Rockwell FTPC, etc\u2022 Familiarity with Agile framework \u2022 Good analytical skills\u2022 Excellent communication skills IMP - TCS Dayone Onsite Location - Saint Petersburg, FL",
        "source": "Email",
        "date_posted": "2024-10-03 12:29:59-05:00",
        "unique_id": "192537281b1983c4",
        "emp_type": [
            "full-time",
            "third party"
        ],
        "tag": "Business Analyst"
    }
]