[
    {
        "company": "Scalable Systems",
        "job_title": "AS400 DB2 Admin",
        "location": "Culver City, CA, USA",
        "full_location": {
            "city": "Culver City",
            "state": "CA",
            "country": "USA"
        },
        "job_details": {
            "employment_type": [
                "third party"
            ],
            "experience_required": "10 & Above",
            "degree_required": "Not specified",
            "visa_sponsorship": "Not specified",
            "notice_period": "Not specified",
            "duration": "Not specified",
            "rate": "Not specified",
            "job_code": ""
        },
        "skills": {
            "core": [
                "AS400",
                "DB2 Admin"
            ],
            "primary": [],
            "secondary": [],
            "all": [
                "AS400",
                "DB2 Admin"
            ]
        },
        "job_type": [],
        "contact_person": "Arbaz Qureshi",
        "email": "arbaz.qureshi@scalable-systems.com",
        "jd": "From: Arbaz Qureshi, Scalable Systems arbaz.qureshi@scalable-systems.com Reply to: arbaz.qureshi@scalable-systems.com Role Description: AS400 DB2 AdminCompetencies: IT IS_AMS_Mainframe_DB2 AdministrationExperience (Years): 10 & AboveEssential Skills: AS400 DB2 AdminDesirable Skills: AS400 DB2 AdminCountry: United StatesBranch | City | Location: TCS - WOODLAND HILLS, CACulver CityCulver City, CA Keywords: AS400 DB2 Admin",
        "source": "Email",
        "date_posted": "2024-10-29 07:30:45-05:00",
        "unique_id": "192d861d4fb42dca",
        "emp_type": [
            "third party"
        ],
        "tag": "DB Admin"
    }
]