[
    {
        "company": "TEK Inspirations LLC",
        "job_title": "Test Automation Engineer with Python",
        "location": "Walnut Creek, CA, USA",
        "full_location": {
            "city": "Walnut Creek",
            "state": "CA",
            "country": "USA"
        },
        "job_details": {
            "employment_type": [
                "contract",
                "third party"
            ],
            "experience_required": "Not specified",
            "degree_required": "Not specified",
            "visa_sponsorship": "Not specified",
            "notice_period": "Not specified",
            "duration": "Long Term",
            "rate": "Not specified"
        },
        "skills": {
            "core": [
                "Python",
                "API Automation",
                "Mobile Automation",
                "Performance/Capacity Tests",
                "Server side Debugging",
                "Linux Basics",
                "CI/CD Tools"
            ],
            "primary": [],
            "secondary": [],
            "all": [
                "Python",
                "API Automation",
                "REST",
                "SOAP",
                "Mobile Automation",
                "Android",
                "iOS",
                "Performance/Capacity Tests",
                "JMeter",
                "Server side Debugging",
                "Linux Basics",
                "CI/CD Tools",
                "Jenkins",
                "Bamboo",
                "Codefresh"
            ]
        },
        "job_type": [
            "hybrid"
        ],
        "contact_person": "Bhawana Arya",
        "email": "bhawana.arya@tekinspirations.com",
        "jd": "From: Bhawana Arya, TEK Inspirations LLC bhawana.arya@tekinspirations.com Reply to: bhawana.arya@tekinspirations.com Hi, Hope you are doing good. Job Description -Need only local to Walnut Creek, CA or nearby!Requirements: Must have a valid LinkedIn profile, valid DL, VISA! Test Automation Engineer with PythonWalnut Creek, CA Hybrid roleLong Term Contract Candidates should come to the office 2 days in a week for sure [Tuesday and Wednesday ] This can be changed to 3 days a week also in future .Will have a Face2Face interview , Coding challenges will be given. Job Description & Must Have Skills : 1.Python Skills 2.API Automation [REST , SOAP]3.Mobile Automation [Android, iOS]4.Performance/Capacity Tests [JMeter] --> Mainly backend 5.Server side Debugging skills 6.Linux Basics 7.CI/CD Tools experience [Jenkins, Bamboo or Codefresh] Thanks and Regards, Bhawana AryaSr. Technical RecruiterTEK Inspirations LLC.| E: bhawana.arya@tekinspirations.com | Desk: +1 469-881-8489LinkedIn: https://www.linkedin.com/in/bhawana-arya-b84947221/W: www.tekinspirations.com",
        "source": "Email",
        "date_posted": "2024-10-21 13:22:12-05:00",
        "unique_id": "192b071088f6fc96",
        "emp_type": [
            "contract",
            "third party"
        ],
        "tag": "Python developer"
    }
]