[
    {
        "company": "fluxteksol.com",
        "job_title": "Senior Java Developer",
        "location": "New York City, NY, USA",
        "full_location": {
            "city": "New York City",
            "state": "NY",
            "country": "USA"
        },
        "job_details": {
            "employment_type": [
                "full-time",
                "third party"
            ],
            "job_code": "",
            "experience_required": "10-12 years",
            "degree_required": "Not specified",
            "visa_sponsorship": "Not specified",
            "notice_period": "Not specified",
            "duration": "Not specified",
            "rate": "Not specified"
        },
        "skills": {
            "core": [
                "Java",
                "Spring Framework",
                "Microservices",
                "AWS"
            ],
            "primary": [
                "Object Oriented Concepts"
            ],
            "secondary": [
                "Search Projects",
                "Search Indexing",
                "Endpoints",
                "Communication Skills"
            ],
            "all": [
                "Java",
                "Spring Framework",
                "Microservices",
                "AWS",
                "Object Oriented Concepts",
                "Search Projects",
                "Search Indexing",
                "Endpoints",
                "Communication Skills"
            ]
        },
        "job_type": [
            "hybrid"
        ],
        "contact_person": "Arjun",
        "email": "arjuna@fluxteksol.com",
        "jd": "From: Arjun, fluxteksol.com arjuna@fluxteksol.com Reply to: arjuna@fluxteksol.com Job Title :Senior Java DeveloperLocation- New York City, NY (Hybrid \u2013 3 days onsite per weekExp: 10-12 _______________________________________________________________ Role: Senior Java DeveloperLocation: New York City, NY (Hybrid \u2013 3 days onsite per week)Local Candidate only. Note: Need 10-12 years\u2019 experience candidateLocal candidate preferred2 Positions available JD:Must have 5 plus years in AWS cloudStrong on Spring framework and micro servicesNeed 10 -12 years of experience Java and object oriented conceptGood to have Worked on Search projects is desirableHaving Search Indexing and End points is plus LinkedIn must be created only before 2018. Passport Number Mandatory 3 Official references. Candidate must have good comm skills.",
        "source": "Email",
        "date_posted": "2024-10-28 14:20:26-05:00",
        "unique_id": "192d4c77cf1d013a",
        "emp_type": [
            "full-time",
            "third party"
        ],
        "tag": "Java developer"
    }
]